{
  "事件概念": {
    "AIsystem": {
      "id": "TwitterPhotoCroppingAlgorithm",
      "中文名称": "Twitter照片裁剪算法",
      "英文名称": "Twitter Photo Crop Algorithm",
      "来源": "Twitter's Photo-Cropping Algorithm Favors Young, Thin Females"
    },
    "Risk": {
      "id": "AlgorithmicBiasInPhotoCropping",
      "中文名称": "照片裁剪中的算法偏见风险",
      "英文名称": "Algorithmic Bias in Photo Cropping Risk",
      "来源": "Twitter's Photo-Cropping Algorithm Favors Young, Thin Females"
    },
    "Consequence": {
      "id": "UnfairRepresentationInSocialMedia",
      "中文名称": "社交媒体中不公平表现的后果",
      "英文名称": "Unfair Representation in Social Media Consequence",
      "来源": "Twitter's Photo-Cropping Algorithm Favors Young, Thin Females"
    },
    "AICapability": {
      "id": "ImageAnalysisAndCropping",
      "中文名称": "图像分析与裁剪能力",
      "英文名称": "Image Handling Capability",
      "来源": "Twitter's Photo-Cropping Algorithm Favors Young, Thin Females"
    },
    "Stakeholder": {
      "id": "TwitterUsers",
      "中文名称": "Twitter用户",
      "英文名称": "Twitter Users",
      "来源": "Twitter's Photo-Cropping Algorithm Favors Young, Thin Females"
    },
    "Impact": {
      "id": "ReinforcementOfBeautyStandards",
      "中文名称": "强化审美标准的影响",
      "英文名称": "Reinforcement of Beauty Standards Impact",
      "来源": "Twitter's Photo-Cropping Algorithm Favors Young, Thin Females"
    },
    "Purpose": {
      "id": "AutomatedImagePresentation",
      "中文名称": "自动图像展示的目的",
      "英文名称": "Automated Image Presentation Purpose",
      "来源": "Twitter's Photo-Cropping Algorithm Favors Young, Thin Females"
    },
    "Domain": {
      "id": "SocialMediaPlatforms",
      "中文名称": "社交媒体平台领域",
      "英文名称": "Social Media Domain",
      "来源": "Twitter's Photo-Cropping Algorithm Favors Young, Thin Females"
    },
    "AITechnique": {
      "id": "ComputerVisionForImageCropping",
      "中文名称": "用于图像裁剪的计算机视觉技术",
      "英文名称": "Computer Vision for Image Cropping Technique",
      "来源": "Twitter's Photo-Cropping Algorithm Favors Young, Thin Females"
    },
    "RiskSource": {
      "id": "BiasedTrainingData",
      "中文名称": "有偏见的训练数据风险源",
      "英文名称": "Training and Content Data Risk",
      "来源": "Twitter's Photo-Cropping Algorithm Favors Young, Thin Females"
    }
  },
  "实体对齐后事件属性": {
    "AIsystem": {
      "id": "TwitterPhotoCroppingAlgorithm",
      "中文名称": "Twitter照片裁剪算法",
      "英文名称": "Twitter Photo Crop Algorithm",
      "来源": "Twitter's Photo-Cropping Algorithm Favors Young, Thin Females"
    },
    "Risk": {
      "id": "AlgorithmicBiasInPhotoCropping",
      "中文名称": "照片裁剪中的算法偏见风险",
      "英文名称": "Algorithmic Bias in Photo Cropping Risk",
      "来源": "Twitter's Photo-Cropping Algorithm Favors Young, Thin Females"
    },
    "Consequence": {
      "id": "UnfairRepresentationInSocialMedia",
      "中文名称": "社交媒体中不公平表现的后果",
      "英文名称": "Unfair Representation in Social Media Consequence",
      "来源": "Twitter's Photo-Cropping Algorithm Favors Young, Thin Females"
    },
    "AICapability": {
      "id": "ImageAnalysisAndCropping",
      "中文名称": "图像分析与裁剪能力",
      "英文名称": "Image Handling Capability",
      "来源": "Twitter's Photo-Cropping Algorithm Favors Young, Thin Females"
    },
    "Stakeholder": {
      "id": "TwitterUsers",
      "中文名称": "Twitter用户",
      "英文名称": "Twitter Users",
      "来源": "Twitter's Photo-Cropping Algorithm Favors Young, Thin Females"
    },
    "Impact": {
      "id": "ReinforcementOfBeautyStandards",
      "中文名称": "强化审美标准的影响",
      "英文名称": "Reinforcement of Beauty Standards Impact",
      "来源": "Twitter's Photo-Cropping Algorithm Favors Young, Thin Females"
    },
    "Purpose": {
      "id": "AutomatedImagePresentation",
      "中文名称": "自动图像展示的目的",
      "英文名称": "Automated Image Presentation Purpose",
      "来源": "Twitter's Photo-Cropping Algorithm Favors Young, Thin Females"
    },
    "Domain": {
      "id": "SocialMediaPlatforms",
      "中文名称": "社交媒体平台领域",
      "英文名称": "Social Media Domain",
      "来源": "Twitter's Photo-Cropping Algorithm Favors Young, Thin Females"
    },
    "AITechnique": {
      "id": "ComputerVisionForImageCropping",
      "中文名称": "用于图像裁剪的计算机视觉技术",
      "英文名称": "Computer Vision for Image Cropping Technique",
      "来源": "Twitter's Photo-Cropping Algorithm Favors Young, Thin Females"
    },
    "RiskSource": {
      "id": "BiasedTrainingData",
      "中文名称": "有偏见的训练数据风险源",
      "英文名称": "Training and Content Data Risk",
      "来源": "Twitter's Photo-Cropping Algorithm Favors Young, Thin Females"
    }
  }
}