{
  "事件概念": {
    "AIsystem": {
      "id": "SuicidePreventionAI",
      "中文名称": "自杀预防AI系统",
      "英文名称": "Suicide Prevention AI System",
      "来源": "Seoul adopts AI for suicide prevention on Han Bridge"
    },
    "Risk": {
      "id": "PrivacyViolationRisk",
      "中文名称": "隐私侵犯风险",
      "英文名称": "Privacy Violation Risk",
      "来源": "Uni boffins train machine learning model on rescue teams' data"
    },
    "AITechnique": {
      "id": "MachineLearningModel",
      "中文名称": "机器学习模型",
      "英文名称": "Machine Learning Model",
      "来源": "Uni boffins train machine learning model on rescue teams' data"
    },
    "Purpose": {
      "id": "SuicidePrevention",
      "中文名称": "自杀预防",
      "英文名称": "Suicide Prevention",
      "来源": "Seoul adopts AI for suicide prevention on Han Bridge"
    },
    "Domain": {
      "id": "PublicSafety",
      "中文名称": "公共安全",
      "英文名称": "Public Safety",
      "来源": "Seoul adopts AI for suicide prevention on Han Bridge"
    }
  }
}