{
  "事件概念": {
    "AIsystem": {
      "id": "AIPoweredInvestmentScamSystem",
      "中文名称": "AI驱动的投资诈骗系统",
      "英文名称": "AI-Powered Investment Scam System",
      "来源": "Six arrested for AI-powered investment scams that stole $20 million"
    },
    "Risk": {
      "id": "FinancialFraudRisk",
      "中文名称": "金融欺诈风险",
      "英文名称": "Financial Fraud Risk",
      "来源": "AI-powered investment scams that stole $20 million"
    },
    "Consequence": {
      "id": "FinancialLoss",
      "中文名称": "经济损失后果",
      "英文名称": "Financial Loss Consequence",
      "来源": "stole $20 million"
    },
    "Stakeholder": {
      "id": "InvestmentScamVictims",
      "中文名称": "投资诈骗受害者",
      "英文名称": "Investment Scam Victims",
      "来源": "stole $20 million"
    },
    "AITechnique": {
      "id": "AIForFraudulentActivities",
      "中文名称": "用于欺诈活动的AI技术",
      "英文名称": "AI for Fraudulent Activities Technique",
      "来源": "AI-powered investment scams"
    }
  }
}