{
  "事件概念": {
    "AIsystem": {
      "id": "ViggleAI",
      "中文名称": "Viggle AI",
      "英文名称": "Viggle AI",
      "来源": "Beware of Viggle AI"
    },
    "Risk": {
      "id": "UncontrollableAICharacterRisk",
      "中文名称": "不可控AI角色风险",
      "英文名称": "AI and Digital Risks",
      "来源": "Viggle Makes Controllable AI Characters for Memes and Visualizing Ideas"
    },
    "AICapability": {
      "id": "CharacterGeneration",
      "中文名称": "角色生成能力",
      "英文名称": "Character Generation Capability",
      "来源": "Viggle Makes Controllable AI Characters for Memes and Visualizing Ideas"
    },
    "Purpose": {
      "id": "MemeCreation",
      "中文名称": "表情包创作目的",
      "英文名称": "Meme Creation Purpose",
      "来源": "Viggle Makes Controllable AI Characters for Memes and Visualizing Ideas"
    },
    "Domain": {
      "id": "SocialMedia",
      "中文名称": "社交媒体领域",
      "英文名称": "Social Media Domain",
      "来源": "Viggle Makes Controllable AI Characters for Memes and Visualizing Ideas"
    }
  },
  "实体对齐后事件属性": {
    "AIsystem": {
      "id": "ViggleAI",
      "中文名称": "Viggle AI",
      "英文名称": "Viggle AI",
      "来源": "Beware of Viggle AI"
    },
    "Risk": {
      "id": "UncontrollableAICharacterRisk",
      "中文名称": "不可控AI角色风险",
      "英文名称": "AI and Digital Risks",
      "来源": "Viggle Makes Controllable AI Characters for Memes and Visualizing Ideas"
    },
    "AICapability": {
      "id": "CharacterGeneration",
      "中文名称": "角色生成能力",
      "英文名称": "Character Generation Capability",
      "来源": "Viggle Makes Controllable AI Characters for Memes and Visualizing Ideas"
    },
    "Purpose": {
      "id": "MemeCreation",
      "中文名称": "表情包创作目的",
      "英文名称": "Meme Creation Purpose",
      "来源": "Viggle Makes Controllable AI Characters for Memes and Visualizing Ideas"
    },
    "Domain": {
      "id": "SocialMedia",
      "中文名称": "社交媒体领域",
      "英文名称": "Social Media Domain",
      "来源": "Viggle Makes Controllable AI Characters for Memes and Visualizing Ideas"
    }
  }
}