{
  "事件概念": {
    "AIsystem": {
      "id": "DeepfakeTechnology",
      "中文名称": "深度伪造技术",
      "英文名称": "Deepfake Technology",
      "来源": "Deepfakes are jumping from porn to politics. It’s time to fight back"
    },
    "Risk": {
      "id": "MisinformationCrisisRisk",
      "中文名称": "虚假信息危机风险",
      "英文名称": "AI and Digital Risks",
      "来源": "Deepfakes are going to worsen the misinformation crisis - and we aren't ready for it"
    },
    "Consequence": {
      "id": "DeepfakePornVideos",
      "中文名称": "深度伪造色情视频后果",
      "英文名称": "Harmful Content & Legal Consequences",
      "来源": "AI expert warns 180,000 deepfake porn videos of innocent people will be online in 2021"
    },
    "AICapability": {
      "id": "FacialManipulationCapability",
      "中文名称": "面部操纵能力",
      "英文名称": "Facial Manipulation & Generation",
      "来源": "Deepfakes are jumping from porn to politics"
    },
    "Stakeholder": {
      "id": "InnocentIndividuals",
      "中文名称": "无辜个人",
      "英文名称": "Innocent People",
      "来源": "AI expert warns 180,000 deepfake porn videos of innocent people will be online in 2021"
    },
    "Impact": {
      "id": "ReputationDamageImpact",
      "中文名称": "声誉损害影响",
      "英文名称": "Trust Erosion & Social Harm",
      "来源": "AI expert warns 180,000 deepfake porn videos of innocent people will be online in 2021"
    },
    "Purpose": {
      "id": "PoliticalManipulationPurpose",
      "中文名称": "政治操纵目的",
      "英文名称": "Political Deceptive Content",
      "来源": "Deepfakes are jumping from porn to politics"
    },
    "Domain": {
      "id": "DigitalMediaDomain",
      "中文名称": "数字媒体领域",
      "英文名称": "Online Content Domain",
      "来源": "Deepfakes are going to worsen the misinformation crisis"
    },
    "AITechnique": {
      "id": "GenerativeAdversarialNetworks",
      "中文名称": "生成对抗网络技术",
      "英文名称": "Generative Adversarial Network",
      "来源": "Deepfakes are jumping from porn to politics"
    },
    "RiskSource": {
      "id": "LackOfRegulationRiskSource",
      "中文名称": "缺乏监管风险源",
      "英文名称": "Legal Deficiency Risk Source",
      "来源": "Deepfakes are going to worsen the misinformation crisis - and we aren't ready for it"
    }
  },
  "实体对齐后事件属性": {
    "AIsystem": {
      "id": "DeepfakeTechnology",
      "中文名称": "深度伪造技术",
      "英文名称": "Deepfake Technology",
      "来源": "Deepfakes are jumping from porn to politics. It’s time to fight back"
    },
    "Risk": {
      "id": "MisinformationCrisisRisk",
      "中文名称": "虚假信息危机风险",
      "英文名称": "AI and Digital Risks",
      "来源": "Deepfakes are going to worsen the misinformation crisis - and we aren't ready for it"
    },
    "Consequence": {
      "id": "DeepfakePornVideos",
      "中文名称": "深度伪造色情视频后果",
      "英文名称": "Harmful Content & Legal Consequences",
      "来源": "AI expert warns 180,000 deepfake porn videos of innocent people will be online in 2021"
    },
    "AICapability": {
      "id": "FacialManipulationCapability",
      "中文名称": "面部操纵能力",
      "英文名称": "Facial Manipulation & Generation",
      "来源": "Deepfakes are jumping from porn to politics"
    },
    "Stakeholder": {
      "id": "InnocentIndividuals",
      "中文名称": "无辜个人",
      "英文名称": "Innocent People",
      "来源": "AI expert warns 180,000 deepfake porn videos of innocent people will be online in 2021"
    },
    "Impact": {
      "id": "ReputationDamageImpact",
      "中文名称": "声誉损害影响",
      "英文名称": "Trust Erosion & Social Harm",
      "来源": "AI expert warns 180,000 deepfake porn videos of innocent people will be online in 2021"
    },
    "Purpose": {
      "id": "PoliticalManipulationPurpose",
      "中文名称": "政治操纵目的",
      "英文名称": "Political Deceptive Content",
      "来源": "Deepfakes are jumping from porn to politics"
    },
    "Domain": {
      "id": "DigitalMediaDomain",
      "中文名称": "数字媒体领域",
      "英文名称": "Online Content Domain",
      "来源": "Deepfakes are going to worsen the misinformation crisis"
    },
    "AITechnique": {
      "id": "GenerativeAdversarialNetworks",
      "中文名称": "生成对抗网络技术",
      "英文名称": "Generative Adversarial Network",
      "来源": "Deepfakes are jumping from porn to politics"
    },
    "RiskSource": {
      "id": "LackOfRegulationRiskSource",
      "中文名称": "缺乏监管风险源",
      "英文名称": "Legal Deficiency Risk Source",
      "来源": "Deepfakes are going to worsen the misinformation crisis - and we aren't ready for it"
    }
  }
}