{
  "事件概念": {
    "AIsystem": {
      "id": "AppleAI",
      "中文名称": "苹果AI系统",
      "英文名称": "Apple AI System",
      "来源": "Grandmother gets X-rated message after Apple AI fail"
    },
    "Risk": {
      "id": "InappropriateContentRisk",
      "中文名称": "不当内容风险",
      "英文名称": "Inappropriate Content Risk",
      "来源": "Grandmother gets X-rated message after Apple AI fail"
    },
    "Consequence": {
      "id": "ExposureToExplicitMaterial",
      "中文名称": "接触不当材料",
      "英文名称": "Exposure to Explicit Material",
      "来源": "Grandmother gets X-rated message after Apple AI fail"
    },
    "AISubject": {
      "id": "ElderlyUser",
      "中文名称": "老年用户",
      "英文名称": "Elderly User",
      "来源": "Grandmother gets X-rated message after Apple AI fail"
    },
    "Impact": {
      "id": "PsychologicalDistress",
      "中文名称": "心理困扰",
      "英文名称": "Psychological Distress",
      "来源": "Grandmother gets X-rated message after Apple AI fail"
    }
  }
}