{
  "事件概念": {
    "AIsystem": {
      "id": "DeepfakeAbuseSite",
      "中文名称": "深度伪造滥用网站",
      "英文名称": "Deepfake Abuse Site",
      "来源": "The Biggest Deepfake Abuse Site Is Growing in Disturbing Ways"
    },
    "Risk": {
      "id": "DeepfakeMisuseRisk",
      "中文名称": "深度伪造滥用风险",
      "英文名称": "Deepfake Misuse Risk",
      "来源": "The Biggest Deepfake Abuse Site Is Growing in Disturbing Ways"
    },
    "RiskSource": {
      "id": "NonConsensualContentCreation",
      "中文名称": "非自愿内容创建",
      "英文名称": "Non-Consensual Content Creation",
      "来源": "The Biggest Deepfake Abuse Site Is Growing in Disturbing Ways"
    },
    "Impact": {
      "id": "PrivacyViolationAndPsychologicalHarm",
      "中文名称": "隐私侵犯和心理伤害",
      "英文名称": "Privacy Violation and Psychological Harm",
      "来源": "The Biggest Deepfake Abuse Site Is Growing in Disturbing Ways"
    },
    "AITechnique": {
      "id": "DeepfakeGenerationTechnology",
      "中文名称": "深度伪造生成技术",
      "英文名称": "Deepfake Generation Technology",
      "来源": "The Biggest Deepfake Abuse Site Is Growing in Disturbing Ways"
    }
  }
}