{
  "事件概念": {
    "AIsystem": {
      "id": "DeepfakePornCreationSystem",
      "中文名称": "深度伪造色情内容生成系统",
      "英文名称": "Deepfake Porn Creation System",
      "来源": "Meloni sues deepfake porn creator ‘to protect women’"
    },
    "Risk": {
      "id": "PrivacyViolationAndReputationDamageRisk",
      "中文名称": "隐私侵犯与名誉损害风险",
      "英文名称": "Privacy Violation and Reputation Damage Risk",
      "来源": "Italian Prime Minister Giorgia Meloni seeking damages of $108,200 in deepfake porn trial"
    },
    "Stakeholder": {
      "id": "ItalianPrimeMinisterGiorgiaMeloni",
      "中文名称": "意大利总理乔治亚·梅洛尼",
      "英文名称": "Italian Prime Minister Giorgia Meloni",
      "来源": "Italy PM Giorgia Meloni to testify today in deepfake pornography trial"
    },
    "Impact": {
      "id": "PersonalReputationDamage",
      "中文名称": "个人名誉损害影响",
      "英文名称": "Personal Reputation Damage Impact",
      "来源": "Meloni sues deepfake porn creator ‘to protect women’"
    },
    "AITechnique": {
      "id": "DeepfakeImageGeneration",
      "中文名称": "深度伪造图像生成技术",
      "英文名称": "Deepfake Image Generation Technique",
      "来源": "Meloni sues deepfake porn creator ‘to protect women’"
    }
  }
}