{
  "事件概念": {
    "AIsystem": {
      "id": "FakeJinDongAI",
      "中文名称": "假冒靳东AI",
      "英文名称": "Fake Jin Dong AI",
      "来源": "靳东回应AI真假靳东"
    },
    "Risk": {
      "id": "IdentityFraudRisk",
      "中文名称": "身份欺诈风险",
      "英文名称": "Identity Fraud Risk",
      "来源": "靳东回应AI真假靳东"
    },
    "Stakeholder": {
      "id": "JinDong",
      "中文名称": "靳东",
      "英文名称": "Jin Dong",
      "来源": "靳东回应AI真假靳东"
    },
    "RiskSource": {
      "id": "DeepfakeTechnology",
      "中文名称": "深度伪造技术",
      "英文名称": "Deepfake Technology",
      "来源": "靳东回应AI真假靳东"
    },
    "Impact": {
      "id": "ReputationDamage",
      "中文名称": "声誉损害",
      "英文名称": "Reputation Damage",
      "来源": "靳东回应AI真假靳东"
    }
  }
}