{
  "事件概念": {
    "AIsystem": {
      "id": "MetaMicrosoftBloombergAI",
      "中文名称": "Meta、微软、彭博AI系统",
      "英文名称": "Meta Microsoft Bloomberg AI System",
      "来源": "Authors sue Meta, Microsoft, Bloomberg in latest AI copyright clash"
    },
    "Risk": {
      "id": "AICopyrightInfringementRisk",
      "中文名称": "AI版权侵权风险",
      "英文名称": "AI and Digital Risks",
      "来源": "Authors sue Meta, Microsoft, Bloomberg in latest AI copyright clash"
    },
    "Stakeholder": {
      "id": "AuthorsAndMikeHuckabee",
      "中文名称": "作者和Mike Huckabee",
      "英文名称": "Authors and Mike Huckabee",
      "来源": "Authors sue Meta, Microsoft, Bloomberg in latest AI copyright clash; The latest AI copyright lawsuit involves Mike Huckabee and his books"
    },
    "AIOperator": {
      "id": "MetaMicrosoftBloomberg",
      "中文名称": "Meta、微软、彭博",
      "英文名称": "Meta Microsoft Bloomberg",
      "来源": "Authors sue Meta, Microsoft, Bloomberg in latest AI copyright clash"
    },
    "Consequence": {
      "id": "LegalActionAgainstAICompanies",
      "中文名称": "对AI公司的法律诉讼后果",
      "英文名称": "Legal Action Against AI Consequences",
      "来源": "Authors sue Meta, Microsoft, Bloomberg in latest AI copyright clash"
    },
    "Domain": {
      "id": "PublishingAndContentCreation",
      "中文名称": "出版和内容创作领域",
      "英文名称": "Media and Publishing",
      "来源": "The latest AI copyright lawsuit involves Mike Huckabee and his books"
    }
  },
  "实体对齐后事件属性": {
    "AIsystem": {
      "id": "MetaMicrosoftBloombergAI",
      "中文名称": "Meta、微软、彭博AI系统",
      "英文名称": "Meta Microsoft Bloomberg AI System",
      "来源": "Authors sue Meta, Microsoft, Bloomberg in latest AI copyright clash"
    },
    "Risk": {
      "id": "AICopyrightInfringementRisk",
      "中文名称": "AI版权侵权风险",
      "英文名称": "AI and Digital Risks",
      "来源": "Authors sue Meta, Microsoft, Bloomberg in latest AI copyright clash"
    },
    "Stakeholder": {
      "id": "AuthorsAndMikeHuckabee",
      "中文名称": "作者和Mike Huckabee",
      "英文名称": "Authors and Mike Huckabee",
      "来源": "Authors sue Meta, Microsoft, Bloomberg in latest AI copyright clash; The latest AI copyright lawsuit involves Mike Huckabee and his books"
    },
    "AIOperator": {
      "id": "MetaMicrosoftBloomberg",
      "中文名称": "Meta、微软、彭博",
      "英文名称": "Meta Microsoft Bloomberg",
      "来源": "Authors sue Meta, Microsoft, Bloomberg in latest AI copyright clash"
    },
    "Consequence": {
      "id": "LegalActionAgainstAICompanies",
      "中文名称": "对AI公司的法律诉讼后果",
      "英文名称": "Legal Action Against AI Consequences",
      "来源": "Authors sue Meta, Microsoft, Bloomberg in latest AI copyright clash"
    },
    "Domain": {
      "id": "PublishingAndContentCreation",
      "中文名称": "出版和内容创作领域",
      "英文名称": "Media and Publishing",
      "来源": "The latest AI copyright lawsuit involves Mike Huckabee and his books"
    }
  }
}