{
  "事件概念": {
    "AIsystem": {
      "id": "AIVoiceCloningTechnology",
      "中文名称": "AI语音克隆技术",
      "英文名称": "AI Voice Cloning Technology",
      "来源": "Cheap AI voice clones may wipe out jobs of 5,000 Australian actors"
    },
    "Risk": {
      "id": "JobDisplacementRisk",
      "中文名称": "职业替代风险",
      "英文名称": "Job Displacement Risk",
      "来源": "Cheap AI voice clones may wipe out jobs of 5,000 Australian actors"
    },
    "Consequence": {
      "id": "ActorJobLoss",
      "中文名称": "演员失业后果",
      "英文名称": "Actor Job Loss Consequence",
      "来源": "Cheap AI voice clones may wipe out jobs of 5,000 Australian actors"
    },
    "Impact": {
      "id": "EconomicImpactOnCreativeIndustry",
      "中文名称": "对创意产业的经济影响",
      "英文名称": "Economic Impact on Creative Industry",
      "来源": "AI is 'direct threat' to Australian creatives, industry says"
    },
    "Stakeholder": {
      "id": "AustralianActors",
      "中文名称": "澳大利亚演员",
      "英文名称": "Australian Actors",
      "来源": "Cheap AI voice clones may wipe out jobs of 5,000 Australian actors"
    },
    "AISubject": {
      "id": "VoiceActors",
      "中文名称": "配音演员",
      "英文名称": "Voice Actors",
      "来源": "Cheap AI voice clones may wipe out jobs of 5,000 Australian actors"
    },
    "Domain": {
      "id": "CreativeIndustry",
      "中文名称": "创意产业领域",
      "英文名称": "Creative Industry Domain",
      "来源": "AI is 'direct threat' to Australian creatives, industry says"
    },
    "RiskSource": {
      "id": "CheapVoiceCloningTechnology",
      "中文名称": "廉价语音克隆技术风险源",
      "英文名称": "Cheap Voice Cloning Technology Risk Source",
      "来源": "Cheap AI voice clones may wipe out jobs of 5,000 Australian actors"
    },
    "AICapability": {
      "id": "VoiceReplicationCapability",
      "中文名称": "语音复制能力",
      "英文名称": "Voice Replication Capability",
      "来源": "Cheap AI voice clones may wipe out jobs of 5,000 Australian actors"
    }
  }
}